kanapy_mtex
