Metadata-Version: 2.4
Name: kanapy-mtex
Version: 6.5.1
Summary: Kanapy MTEX backend (requires Matlab installation)
Author: Mahesh R.G. Prasad, Abhishek Biswas, Golsa Tolooei Eshlaghi, Ronak Shoghi, Napat Vajragupta, Yousef Rezek, Hrushikesh Uday Bhimavarapu
Author-email: Alexander Hartmaier <alexander.hartmaier@rub.de>
License-Expression: AGPL-3.0-or-later
Classifier: Development Status :: 4 - Beta
Classifier: Intended Audience :: Science/Research
Classifier: Natural Language :: English
Classifier: Programming Language :: Python :: 3.9
Classifier: Programming Language :: Python :: 3.10
Classifier: Programming Language :: Python :: 3.11
Classifier: Programming Language :: Python :: 3.12
Classifier: Topic :: Scientific/Engineering :: Physics
Requires-Python: <3.13,>=3.9
License-File: LICENSE
Requires-Dist: kanapy>=6.5.0
Dynamic: license-file
